MANIFEST.in
README.md
pandoc-listof-sample.md
pandoc_listof.py
setup.cfg
setup.py
pandoc_listof.egg-info/PKG-INFO
pandoc_listof.egg-info/SOURCES.txt
pandoc_listof.egg-info/dependency_links.txt
pandoc_listof.egg-info/entry_points.txt
pandoc_listof.egg-info/requires.txt
pandoc_listof.egg-info/top_level.txt