Metadata-Version: 1.1
Name: pandoc-listof
Version: 0.3.1
Summary: A pandoc filter for automatic creation of lists
Home-page: https://github.com/chdemko/pandoc-listof
Author: Christophe Demko
Author-email: chdemko@gmail.com
License: CeCILL-B
Download-URL: https://github.com/chdemko/pandoc-listof/archive/master.zip
Keywords: pandoc,filters,list
Platform: UNKNOWN
Classifier: Development Status :: 7 - Inactive
Classifier: Operating System :: OS Independent
Classifier: Environment :: Console
Classifier: Intended Audience :: End Users/Desktop
Classifier: Intended Audience :: Developers
Classifier: Topic :: Software Development :: Build Tools
Classifier: Topic :: Software Development :: Documentation
Classifier: Topic :: Text Processing :: Filters
Classifier: Programming Language :: Python :: 2.7
Classifier: Programming Language :: Python :: 3.3
Classifier: Programming Language :: Python :: 3.4
Classifier: Programming Language :: Python :: 3.5
Classifier: Natural Language :: English
